iroha/__init__.py
iroha/block_pb2.py
iroha/commands_pb2.py
iroha/ed25519.py
iroha/endpoint_pb2.py
iroha/endpoint_pb2_grpc.py
iroha/iroha.py
iroha/primitive_pb2.py
iroha/proposal_pb2.py
iroha/qry_responses_pb2.py
iroha/queries_pb2.py
iroha/transaction_pb2.py
iroha-1.6.0.2.dist-info/LICENSE
iroha-1.6.0.2.dist-info/METADATA
iroha-1.6.0.2.dist-info/WHEEL
iroha-1.6.0.2.dist-info/top_level.txt
iroha-1.6.0.2.dist-info/RECORD
