Metadata-Version: 2.1
Name: iroha
Version: 1.6.0.2
Summary: Python library for Hyperledger Iroha
Home-page: https://github.com/hyperledger/iroha-python
Author: Soramitsu Co Ltd
Author-email: admin@soramitsu.co.jp
License: Apache-2.0
Project-URL: Jenkins, https://jenkins.soramitsu.co.jp/
Project-URL: Nexus, https://nexus.iroha.tech/
Project-URL: Documentation, https://iroha.readthedocs.io/en/latest/
Project-URL: Doxygen, https://docs.iroha.tech/
Project-URL: Source Code, https://github.com/hyperledger/iroha-python
Classifier: Programming Language :: Python :: 3
Classifier: Operating System :: OS Independent
License-File: LICENSE
Requires-Dist: protobuf>=3.8.0
Requires-Dist: protobuf<=3.20.1
Requires-Dist: grpcio-tools>=1.12.1
Requires-Dist: pysha3; python_version < "3.6"
Requires-Dist: pynacl>=1.4.0
